vk_parsing/__init__.py
vk_parsing/api.py
vk_parsing/exceptions.py
vk_parsing/lconfig.py
vk_parsing/parser.py
vk_parsing/task.py
vk_parsing/accounts/account.py
vk_parsing/accounts/sync_account.py
vk_parsing-0.0.1.5.dist-info/LICENSE
vk_parsing-0.0.1.5.dist-info/METADATA
vk_parsing-0.0.1.5.dist-info/WHEEL
vk_parsing-0.0.1.5.dist-info/top_level.txt
vk_parsing-0.0.1.5.dist-info/RECORD
